hw/src/core/instr_mem.vhd
-- instr_mem.vhd - Simple instruction ROM (read-only) with file init
-- Copyright (C) 2025  4137314
-- GNU GPLv3

library IEEE;
use IEEE.STD_LOGIC_1164.ALL;
use IEEE.NUMERIC_STD.ALL;
use std.textio.all;
-- Required for hread (hex read)
use ieee.std_logic_textio.all;

entity instr_mem is
    generic (
        ADDR_WIDTH : integer := 10; -- 2^10 = 1024 words
        INIT_FILE  : string  := ""  -- Path to hex file
    );
    port (
        clk     : in  std_logic;
        addr    : in  std_logic_vector(31 downto 0); -- byte address (PC)
        instr   : out std_logic_vector(31 downto 0)
    );
end entity;

architecture rtl of instr_mem is
    constant DEPTH : integer := 2**ADDR_WIDTH;
    type mem_t is array (0 to DEPTH-1) of std_logic_vector(31 downto 0);
    
    -- Initialize with NOPs (0x00000013 is 'addi x0, x0, 0' in RISC-V)
    signal rom : mem_t := (others => x"00000013");
    signal word_addr_idx : integer range 0 to DEPTH-1;
begin

    -- Combinational address decoding
    -- Shift right by 2 to convert byte address to word index
    word_addr_idx <= to_integer(unsigned(addr(ADDR_WIDTH + 1 downto 2)));

    -- Combinational read
    instr <= rom(word_addr_idx);

    -- Initialization process (Simulation only)
    init_proc: process
        file f           : text;
        variable line_in : line;
        variable i       : integer := 0;
        variable sval    : std_logic_vector(31 downto 0);
        variable status  : file_open_status;
        -- FIXED: Variable 's' moved here, before 'begin'
        variable s       : string(1 to 100); 
    begin
        if INIT_FILE /= "" then
            file_open(status, f, INIT_FILE, read_mode);
            
            if status = open_ok then
                while not endfile(f) and i < DEPTH loop
                    readline(f, line_in);
                    -- Use hread to parse hex strings directly into std_logic_vector
                    hread(line_in, sval);
                    rom(i) <= sval;
                    i := i + 1;
                end loop;
                file_close(f);
            else
                report "[INSTR_MEM] Could not open INIT_FILE: " & INIT_FILE severity warning;
            end if;
        end if;
        wait; -- Process runs only once at start of simulation
    end process init_proc;

end architecture;

hw/src/top/riscv.vhd
-- riscv.vhd - Top-level wrapper for the RV32I Core
-- Copyright (C) 2025  4137314

library ieee;
use ieee.std_logic_1164.all;
use ieee.numeric_std.all;

library work;
use work.riscv_pkg.all;

entity riscv is
    port (
        clk_i : in  std_logic;
        rst_i : in  std_logic;
        
        -- Basic External Interface (for debugging/RAM)
        trap_o : out std_logic
    );
end entity riscv;
architecture top of riscv is
    -- Internal signals
    signal pc_next    : std_logic_vector(31 downto 0);
    signal pc_current : std_logic_vector(31 downto 0);
    signal instr      : std_logic_vector(31 downto 0);
begin

    -- 1. Instruction Memory Instance
    i_imem : entity work.instr_mem
        generic map (
            ADDR_WIDTH => 12,           -- 4KB
            INIT_FILE  => "program.hex" -- Ensure this file exists in your project root
        )
        port map (
            clk   => clk_i,
            addr  => pc_current,
            instr => instr
        );

    -- 2. PC Update Logic
    process(clk_i)
    begin
        if rising_edge(clk_i) then
            if rst_i = '1' then
                pc_current <= (others => '0');
            else
                pc_current <= pc_next;
            end if;
        end if;
    end process;

    -- 3. Next PC (Simple increment for now, until we handle Branches/Jumps)
    pc_next <= std_logic_vector(unsigned(pc_current) + 4);

end architecture;

hw/tb/system/tb_riscv_core.vhd
library ieee;
use ieee.std_logic_1164.all;
use ieee.numeric_std.all;

library work;
use work.riscv_pkg.all;
use work.tb_utils_pkg.all;

entity tb_riscv_core is
end entity tb_riscv_core;

architecture sim of tb_riscv_core is
    -- Global Signals
    signal clk   : std_logic := '0';
    signal rst   : std_logic := '1';

    -- Memory Interface (if exposed at top level)
    signal instr_addr : std_logic_vector(31 downto 0);
    signal instr_data : std_logic_vector(31 downto 0);

begin

    -- 1. Clock Generation (using your utility)
    clk_gen_proc: process
    begin
        while now < 1000 ns loop  -- Adjust simulation timeout as needed
            clk <= '0'; wait for 5 ns;
            clk <= '1'; wait for 5 ns;
        end loop;
        wait;
    end process;

    -- 2. Instantiate the RISC-V Top Level
    -- Note: Update the entity name and ports to match your 'hw/src/top/riscv.vhd'
    dut: entity work.riscv
        port map (
            clk_i => clk,
            rst_i => rst
            -- Add other ports like memory interfaces here
        );

    -- 3. Stimulus Process
    stim_proc: process
    begin
        log_info("Initializing RISC-V System Simulation...");
        
        -- Hold reset for a few cycles
        rst <= '1';
        wait_cycles(clk, 5);
        rst <= '0';
        
        log_info("System out of reset. Execution started.");

        -- Let the processor run for a while
        wait for 500 ns;

        log_info("Simulation window reached. Check waveforms for execution flow.");
        wait;
    end process;

end architecture sim;

hw/build/tb_riscv_core.vcd
$date
  Thu Mar 19 16:53:54 2026
$end
$version
  GHDL v0
$end
$timescale
  1 fs
$end
$scope module standard $end
$upscope $end
$scope module textio $end
$upscope $end
$scope module std_logic_1164 $end
$upscope $end
$scope module numeric_std $end
$upscope $end
$scope module riscv_pkg $end
$upscope $end
$scope module tb_utils_pkg $end
$upscope $end
$scope module std_logic_textio $end
$upscope $end
$scope module tb_riscv_core $end
$var reg 1 ! clk $end
$var reg 1 " rst $end
$var reg 32 # instr_addr[31:0] $end
$var reg 32 $ instr_data[31:0] $end
$scope module dut $end
$var reg 1 % clk_i $end
$var reg 1 & rst_i $end
$var reg 1 ' trap_o $end
$var reg 32 ( pc_next[31:0] $end
$var reg 32 ) pc_current[31:0] $end
$var reg 32 * instr[31:0] $end
$scope module i_imem $end
$var reg 1 + clk $end
$var reg 32 , addr[31:0] $end
$var reg 32 - instr[31:0] $end
$comment rom is not handled $end
$var integer 32 . word_addr_idx $end
$upscope $end
$upscope $end
$upscope $end
$enddefinitions $end
#0
0!
1"
bUUUUUUUUUUUUUUUUUUUUUUUUUUUUUUUU #
bUUUUUUUUUUUUUUUUUUUUUUUUUUUUUUUU $
0%
1&
U'
bXXXXXXXXXXXXXXXXXXXXXXXXXXXXXXXX (
bUUUUUUUUUUUUUUUUUUUUUUUUUUUUUUUU )
b00000000000000000000000000010011 *
0+
bUUUUUUUUUUUUUUUUUUUUUUUUUUUUUUUU ,
b00000000000000000000000000010011 -
b0 .
#5000000
1!
1%
b00000000000000000000000000000100 (
b00000000000000000000000000000000 )
1+
b00000000000000000000000000000000 ,
#10000000
0!
0%
0+
#15000000
1!
1%
1+
#20000000
0!
0%
0+
#25000000
1!
1%
1+
#30000000
0!
0%
0+
#35000000
1!
1%
1+
#40000000
0!
0%
0+
#45000000
1!
0"
1%
0&
1+
#50000000
0!
0%
0+
#55000000
1!
1%
b00000000000000000000000000001000 (
b00000000000000000000000000000100 )
1+
b00000000000000000000000000000100 ,
b1 .
#60000000
0!
0%
0+
#65000000
1!
1%
b00000000000000000000000000001100 (
b00000000000000000000000000001000 )
1+
b00000000000000000000000000001000 ,
b10 .
#70000000
0!
0%
0+
#75000000
1!
1%
b00000000000000000000000000010000 (
b00000000000000000000000000001100 )
1+
b00000000000000000000000000001100 ,
b11 .
#80000000
0!
0%
0+
#85000000
1!
1%
b00000000000000000000000000010100 (
b00000000000000000000000000010000 )
1+
b00000000000000000000000000010000 ,
b100 .
#90000000
0!
0%
0+
#95000000
1!
1%
b00000000000000000000000000011000 (
b00000000000000000000000000010100 )
1+
b00000000000000000000000000010100 ,
b101 .
#100000000
0!
0%
0+
#105000000
1!
1%
b00000000000000000000000000011100 (
b00000000000000000000000000011000 )
1+
b00000000000000000000000000011000 ,
b110 .
#110000000
0!
0%
0+
#115000000
1!
1%
b00000000000000000000000000100000 (
b00000000000000000000000000011100 )
1+
b00000000000000000000000000011100 ,
b111 .
#120000000
0!
0%
0+
#125000000
1!
1%
b00000000000000000000000000100100 (
b00000000000000000000000000100000 )
1+
b00000000000000000000000000100000 ,
b1000 .
#130000000
0!
0%
0+
#135000000
1!
1%
b00000000000000000000000000101000 (
b00000000000000000000000000100100 )
1+
b00000000000000000000000000100100 ,
b1001 .
#140000000
0!
0%
0+
#145000000
1!
1%
b00000000000000000000000000101100 (
b00000000000000000000000000101000 )
1+
b00000000000000000000000000101000 ,
b1010 .
#150000000
0!
0%
0+
#155000000
1!
1%
b00000000000000000000000000110000 (
b00000000000000000000000000101100 )
1+
b00000000000000000000000000101100 ,
b1011 .
#160000000
0!
0%
0+
#165000000
1!
1%
b00000000000000000000000000110100 (
b00000000000000000000000000110000 )
1+
b00000000000000000000000000110000 ,
b1100 .
#170000000
0!
0%
0+
#175000000
1!
1%
b00000000000000000000000000111000 (
b00000000000000000000000000110100 )
1+
b00000000000000000000000000110100 ,
b1101 .
#180000000
0!
0%
0+
#185000000
1!
1%
b00000000000000000000000000111100 (
b00000000000000000000000000111000 )
1+
b00000000000000000000000000111000 ,
b1110 .
#190000000
0!
0%
0+
#195000000
1!
1%
b00000000000000000000000001000000 (
b00000000000000000000000000111100 )
1+
b00000000000000000000000000111100 ,
b1111 .
#200000000
0!
0%
0+
#205000000
1!
1%
b00000000000000000000000001000100 (
b00000000000000000000000001000000 )
1+
b00000000000000000000000001000000 ,
b10000 .
#210000000
0!
0%
0+
#215000000
1!
1%
b00000000000000000000000001001000 (
b00000000000000000000000001000100 )
1+
b00000000000000000000000001000100 ,
b10001 .
#220000000
0!
0%
0+
#225000000
1!
1%
b00000000000000000000000001001100 (
b00000000000000000000000001001000 )
1+
b00000000000000000000000001001000 ,
b10010 .
#230000000
0!
0%
0+
#235000000
1!
1%
b00000000000000000000000001010000 (
b00000000000000000000000001001100 )
1+
b00000000000000000000000001001100 ,
b10011 .
#240000000
0!
0%
0+
#245000000
1!
1%
b00000000000000000000000001010100 (
b00000000000000000000000001010000 )
1+
b00000000000000000000000001010000 ,
b10100 .
#250000000
0!
0%
0+
#255000000
1!
1%
b00000000000000000000000001011000 (
b00000000000000000000000001010100 )
1+
b00000000000000000000000001010100 ,
b10101 .
#260000000
0!
0%
0+
#265000000
1!
1%
b00000000000000000000000001011100 (
b00000000000000000000000001011000 )
1+
b00000000000000000000000001011000 ,
b10110 .
#270000000
0!
0%
0+
#275000000
1!
1%
b00000000000000000000000001100000 (
b00000000000000000000000001011100 )
1+
b00000000000000000000000001011100 ,
b10111 .
#280000000
0!
0%
0+
#285000000
1!
1%
b00000000000000000000000001100100 (
b00000000000000000000000001100000 )
1+
b00000000000000000000000001100000 ,
b11000 .
#290000000
0!
0%
0+
#295000000
1!
1%
b00000000000000000000000001101000 (
b00000000000000000000000001100100 )
1+
b00000000000000000000000001100100 ,
b11001 .
#300000000
0!
0%
0+
#305000000
1!
1%
b00000000000000000000000001101100 (
b00000000000000000000000001101000 )
1+
b00000000000000000000000001101000 ,
b11010 .
#310000000
0!
0%
0+
#315000000
1!
1%
b00000000000000000000000001110000 (
b00000000000000000000000001101100 )
1+
b00000000000000000000000001101100 ,
b11011 .
#320000000
0!
0%
0+
#325000000
1!
1%
b00000000000000000000000001110100 (
b00000000000000000000000001110000 )
1+
b00000000000000000000000001110000 ,
b11100 .
#330000000
0!
0%
0+
#335000000
1!
1%
b00000000000000000000000001111000 (
b00000000000000000000000001110100 )
1+
b00000000000000000000000001110100 ,
b11101 .
#340000000
0!
0%
0+
#345000000
1!
1%
b00000000000000000000000001111100 (
b00000000000000000000000001111000 )
1+
b00000000000000000000000001111000 ,
b11110 .
#350000000
0!
0%
0+
#355000000
1!
1%
b00000000000000000000000010000000 (
b00000000000000000000000001111100 )
1+
b00000000000000000000000001111100 ,
b11111 .
#360000000
0!
0%
0+
#365000000
1!
1%
b00000000000000000000000010000100 (
b00000000000000000000000010000000 )
1+
b00000000000000000000000010000000 ,
b100000 .
#370000000
0!
0%
0+
#375000000
1!
1%
b00000000000000000000000010001000 (
b00000000000000000000000010000100 )
1+
b00000000000000000000000010000100 ,
b100001 .
#380000000
0!
0%
0+
#385000000
1!
1%
b00000000000000000000000010001100 (
b00000000000000000000000010001000 )
1+
b00000000000000000000000010001000 ,
b100010 .
#390000000
0!
0%
0+
#395000000
1!
1%
b00000000000000000000000010010000 (
b00000000000000000000000010001100 )
1+
b00000000000000000000000010001100 ,
b100011 .
#400000000
0!
0%
0+
#405000000
1!
1%
b00000000000000000000000010010100 (
b00000000000000000000000010010000 )
1+
b00000000000000000000000010010000 ,
b100100 .
#410000000
0!
0%
0+
#415000000
1!
1%
b00000000000000000000000010011000 (
b00000000000000000000000010010100 )
1+
b00000000000000000000000010010100 ,
b100101 .
#420000000
0!
0%
0+
#425000000
1!
1%
b00000000000000000000000010011100 (
b00000000000000000000000010011000 )
1+
b00000000000000000000000010011000 ,
b100110 .
#430000000
0!
0%
0+
#435000000
1!
1%
b00000000000000000000000010100000 (
b00000000000000000000000010011100 )
1+
b00000000000000000000000010011100 ,
b100111 .
#440000000
0!
0%
0+
#445000000
1!
1%
b00000000000000000000000010100100 (
b00000000000000000000000010100000 )
1+
b00000000000000000000000010100000 ,
b101000 .
#450000000
0!
0%
0+
#455000000
1!
1%
b00000000000000000000000010101000 (
b00000000000000000000000010100100 )
1+
b00000000000000000000000010100100 ,
b101001 .
#460000000
0!
0%
0+
#465000000
1!
1%
b00000000000000000000000010101100 (
b00000000000000000000000010101000 )
1+
b00000000000000000000000010101000 ,
b101010 .
#470000000
0!
0%
0+
#475000000
1!
1%
b00000000000000000000000010110000 (
b00000000000000000000000010101100 )
1+
b00000000000000000000000010101100 ,
b101011 .
#480000000
0!
0%
0+
#485000000
1!
1%
b00000000000000000000000010110100 (
b00000000000000000000000010110000 )
1+
b00000000000000000000000010110000 ,
b101100 .
#490000000
0!
0%
0+
#495000000
1!
1%
b00000000000000000000000010111000 (
b00000000000000000000000010110100 )
1+
b00000000000000000000000010110100 ,
b101101 .
#500000000
0!
0%
0+
#505000000
1!
1%
b00000000000000000000000010111100 (
b00000000000000000000000010111000 )
1+
b00000000000000000000000010111000 ,
b101110 .
#510000000
0!
0%
0+
#515000000
1!
1%
b00000000000000000000000011000000 (
b00000000000000000000000010111100 )
1+
b00000000000000000000000010111100 ,
b101111 .
#520000000
0!
0%
0+
#525000000
1!
1%
b00000000000000000000000011000100 (
b00000000000000000000000011000000 )
1+
b00000000000000000000000011000000 ,
b110000 .
#530000000
0!
0%
0+
#535000000
1!
1%
b00000000000000000000000011001000 (
b00000000000000000000000011000100 )
1+
b00000000000000000000000011000100 ,
b110001 .
#540000000
0!
0%
0+
#545000000
1!
1%
b00000000000000000000000011001100 (
b00000000000000000000000011001000 )
1+
b00000000000000000000000011001000 ,
b110010 .
#550000000
0!
0%
0+
#555000000
1!
1%
b00000000000000000000000011010000 (
b00000000000000000000000011001100 )
1+
b00000000000000000000000011001100 ,
b110011 .
#560000000
0!
0%
0+
#565000000
1!
1%
b00000000000000000000000011010100 (
b00000000000000000000000011010000 )
1+
b00000000000000000000000011010000 ,
b110100 .
#570000000
0!
0%
0+
#575000000
1!
1%
b00000000000000000000000011011000 (
b00000000000000000000000011010100 )
1+
b00000000000000000000000011010100 ,
b110101 .
#580000000
0!
0%
0+
#585000000
1!
1%
b00000000000000000000000011011100 (
b00000000000000000000000011011000 )
1+
b00000000000000000000000011011000 ,
b110110 .
#590000000
0!
0%
0+
#595000000
1!
1%
b00000000000000000000000011100000 (
b00000000000000000000000011011100 )
1+
b00000000000000000000000011011100 ,
b110111 .
#600000000
0!
0%
0+
#605000000
1!
1%
b00000000000000000000000011100100 (
b00000000000000000000000011100000 )
1+
b00000000000000000000000011100000 ,
b111000 .
#610000000
0!
0%
0+
#615000000
1!
1%
b00000000000000000000000011101000 (
b00000000000000000000000011100100 )
1+
b00000000000000000000000011100100 ,
b111001 .
#620000000
0!
0%
0+
#625000000
1!
1%
b00000000000000000000000011101100 (
b00000000000000000000000011101000 )
1+
b00000000000000000000000011101000 ,
b111010 .
#630000000
0!
0%
0+
#635000000
1!
1%
b00000000000000000000000011110000 (
b00000000000000000000000011101100 )
1+
b00000000000000000000000011101100 ,
b111011 .
#640000000
0!
0%
0+
#645000000
1!
1%
b00000000000000000000000011110100 (
b00000000000000000000000011110000 )
1+
b00000000000000000000000011110000 ,
b111100 .
#650000000
0!
0%
0+
#655000000
1!
1%
b00000000000000000000000011111000 (
b00000000000000000000000011110100 )
1+
b00000000000000000000000011110100 ,
b111101 .
#660000000
0!
0%
0+
#665000000
1!
1%
b00000000000000000000000011111100 (
b00000000000000000000000011111000 )
1+
b00000000000000000000000011111000 ,
b111110 .
#670000000
0!
0%
0+
#675000000
1!
1%
b00000000000000000000000100000000 (
b00000000000000000000000011111100 )
1+
b00000000000000000000000011111100 ,
b111111 .
#680000000
0!
0%
0+
#685000000
1!
1%
b00000000000000000000000100000100 (
b00000000000000000000000100000000 )
1+
b00000000000000000000000100000000 ,
b1000000 .
#690000000
0!
0%
0+
#695000000
1!
1%
b00000000000000000000000100001000 (
b00000000000000000000000100000100 )
1+
b00000000000000000000000100000100 ,
b1000001 .
#700000000
0!
0%
0+
#705000000
1!
1%
b00000000000000000000000100001100 (
b00000000000000000000000100001000 )
1+
b00000000000000000000000100001000 ,
b1000010 .
#710000000
0!
0%
0+
#715000000
1!
1%
b00000000000000000000000100010000 (
b00000000000000000000000100001100 )
1+
b00000000000000000000000100001100 ,
b1000011 .
#720000000
0!
0%
0+
#725000000
1!
1%
b00000000000000000000000100010100 (
b00000000000000000000000100010000 )
1+
b00000000000000000000000100010000 ,
b1000100 .
#730000000
0!
0%
0+
#735000000
1!
1%
b00000000000000000000000100011000 (
b00000000000000000000000100010100 )
1+
b00000000000000000000000100010100 ,
b1000101 .
#740000000
0!
0%
0+
#745000000
1!
1%
b00000000000000000000000100011100 (
b00000000000000000000000100011000 )
1+
b00000000000000000000000100011000 ,
b1000110 .
#750000000
0!
0%
0+
#755000000
1!
1%
b00000000000000000000000100100000 (
b00000000000000000000000100011100 )
1+
b00000000000000000000000100011100 ,
b1000111 .
#760000000
0!
0%
0+
#765000000
1!
1%
b00000000000000000000000100100100 (
b00000000000000000000000100100000 )
1+
b00000000000000000000000100100000 ,
b1001000 .
#770000000
0!
0%
0+
#775000000
1!
1%
b00000000000000000000000100101000 (
b00000000000000000000000100100100 )
1+
b00000000000000000000000100100100 ,
b1001001 .
#780000000
0!
0%
0+
#785000000
1!
1%
b00000000000000000000000100101100 (
b00000000000000000000000100101000 )
1+
b00000000000000000000000100101000 ,
b1001010 .
#790000000
0!
0%
0+
#795000000
1!
1%
b00000000000000000000000100110000 (
b00000000000000000000000100101100 )
1+
b00000000000000000000000100101100 ,
b1001011 .
#800000000
0!
0%
0+
#805000000
1!
1%
b00000000000000000000000100110100 (
b00000000000000000000000100110000 )
1+
b00000000000000000000000100110000 ,
b1001100 .
#810000000
0!
0%
0+
#815000000
1!
1%
b00000000000000000000000100111000 (
b00000000000000000000000100110100 )
1+
b00000000000000000000000100110100 ,
b1001101 .
#820000000
0!
0%
0+
#825000000
1!
1%
b00000000000000000000000100111100 (
b00000000000000000000000100111000 )
1+
b00000000000000000000000100111000 ,
b1001110 .
#830000000
0!
0%
0+
#835000000
1!
1%
b00000000000000000000000101000000 (
b00000000000000000000000100111100 )
1+
b00000000000000000000000100111100 ,
b1001111 .
#840000000
0!
0%
0+
#845000000
1!
1%
b00000000000000000000000101000100 (
b00000000000000000000000101000000 )
1+
b00000000000000000000000101000000 ,
b1010000 .
#850000000
0!
0%
0+
#855000000
1!
1%
b00000000000000000000000101001000 (
b00000000000000000000000101000100 )
1+
b00000000000000000000000101000100 ,
b1010001 .
#860000000
0!
0%
0+
#865000000
1!
1%
b00000000000000000000000101001100 (
b00000000000000000000000101001000 )
1+
b00000000000000000000000101001000 ,
b1010010 .
#870000000
0!
0%
0+
#875000000
1!
1%
b00000000000000000000000101010000 (
b00000000000000000000000101001100 )
1+
b00000000000000000000000101001100 ,
b1010011 .
#880000000
0!
0%
0+
#885000000
1!
1%
b00000000000000000000000101010100 (
b00000000000000000000000101010000 )
1+
b00000000000000000000000101010000 ,
b1010100 .
#890000000
0!
0%
0+
#895000000
1!
1%
b00000000000000000000000101011000 (
b00000000000000000000000101010100 )
1+
b00000000000000000000000101010100 ,
b1010101 .
#900000000
0!
0%
0+
#905000000
1!
1%
b00000000000000000000000101011100 (
b00000000000000000000000101011000 )
1+
b00000000000000000000000101011000 ,
b1010110 .
#910000000
0!
0%
0+
#915000000
1!
1%
b00000000000000000000000101100000 (
b00000000000000000000000101011100 )
1+
b00000000000000000000000101011100 ,
b1010111 .
#920000000
0!
0%
0+
#925000000
1!
1%
b00000000000000000000000101100100 (
b00000000000000000000000101100000 )
1+
b00000000000000000000000101100000 ,
b1011000 .
#930000000
0!
0%
0+
#935000000
1!
1%
b00000000000000000000000101101000 (
b00000000000000000000000101100100 )
1+
b00000000000000000000000101100100 ,
b1011001 .
#940000000
0!
0%
0+
#945000000
1!
1%
b00000000000000000000000101101100 (
b00000000000000000000000101101000 )
1+
b00000000000000000000000101101000 ,
b1011010 .
#950000000
0!
0%
0+
#955000000
1!
1%
b00000000000000000000000101110000 (
b00000000000000000000000101101100 )
1+
b00000000000000000000000101101100 ,
b1011011 .
#960000000
0!
0%
0+
#965000000
1!
1%
b00000000000000000000000101110100 (
b00000000000000000000000101110000 )
1+
b00000000000000000000000101110000 ,
b1011100 .
#970000000
0!
0%
0+
#975000000
1!
1%
b00000000000000000000000101111000 (
b00000000000000000000000101110100 )
1+
b00000000000000000000000101110100 ,
b1011101 .
#980000000
0!
0%
0+
#985000000
1!
1%
b00000000000000000000000101111100 (
b00000000000000000000000101111000 )
1+
b00000000000000000000000101111000 ,
b1011110 .
#990000000
0!
0%
0+
#995000000
1!
1%
b00000000000000000000000110000000 (
b00000000000000000000000101111100 )
1+
b00000000000000000000000101111100 ,
b1011111 .
